hypixelez/__init__.py
hypixelez/hypixel_api.py
hypixelez/logger.py
hypixelez-1.0.1.dist-info/METADATA
hypixelez-1.0.1.dist-info/WHEEL
hypixelez-1.0.1.dist-info/top_level.txt
hypixelez-1.0.1.dist-info/RECORD
