Metadata-Version: 2.4
Name: hypixelez
Version: 1.0.1
Summary: Python library for easy interaction with Hypixel API, specifically designed for SkyBlock profile data
Author-email: Onii-Chan <skobochki.ad@mail.ru>
License: MIT
Project-URL: Homepage, https://github.com/SerJo2/hypixelez
Project-URL: Repository, https://github.com/SerJo2/hypixelez
Project-URL: Issues, https://github.com/SerJo2/hypixelez/issues
Project-URL: Changelog, https://github.com/SerJo2/hypixelez/blob/main/CHANGELOG.md
Keywords: hypixel,minecraft,skyblock,api,gaming
Classifier: Development Status :: 5 - Production/Stable
Classifier: Intended Audience :: Developers
Classifier: Intended Audience :: Education
Classifier: Topic :: Software Development :: Libraries :: Python Modules
Classifier: Topic :: Games/Entertainment
Classifier: Programming Language :: Python :: 3
Classifier: Programming Language :: Python :: 3.9
Classifier: Programming Language :: Python :: 3.10
Classifier: Programming Language :: Python :: 3.11
Classifier: Programming Language :: Python :: 3.12
Classifier: Operating System :: OS Independent
Requires-Python: >=3.9
Requires-Dist: requests>=2.32.5
Provides-Extra: test
Requires-Dist: pytest>=6.0; extra == "test"
Requires-Dist: pytest-cov; extra == "test"
Requires-Dist: python-dotenv; extra == "test"
